Metadata-Version: 1.0
Name: pyjournal
Version: 0.1.4
Summary: An app for personal journaling
Home-page: UNKNOWN
Author: UNKNOWN
Author-email: UNKNOWN
License: UNKNOWN
Platform: UNKNOWN
